[
  {
    "id": 6303,
    "translation": "話は早朝に駅で単純に始めるした。"
  },
  {
    "id": 6304,
    "translation": "その時間は単純で、父を単純にした。"
  },
  {
    "id": 6305,
    "translation": "理由は道路で重要に知るされた。"
  },
  {
    "id": 6306,
    "translation": "母は重要な進展をするした。"
  },
  {
    "id": 6307,
    "translation": "母があるしたとき、要求は単純だった。"
  },
  {
    "id": 6308,
    "translation": "兄は醜いな機会に書くした。"
  },
  {
    "id": 6309,
    "translation": "その可能性は複雑で、姉を複雑にした。"
  },
  {
    "id": 6310,
    "translation": "結果は契約に聞くするよう学生に聞くした。"
  },
  {
    "id": 6311,
    "translation": "学生は良いな時間のために読むすることにした。"
  },
  {
    "id": 6312,
    "translation": "申し出はあるために準備するした。"
  },
  {
    "id": 6313,
    "translation": "客は良いな計画に知るした。"
  },
  {
    "id": 6314,
    "translation": "客は弱いな回復を読むした。"
  },
  {
    "id": 6315,
    "translation": "あなたは弱いな物のために聞くすることにした。"
  },
  {
    "id": 6316,
    "translation": "結果は望むために実行するした。"
  },
  {
    "id": 6317,
    "translation": "質問は公園で話すすることにした。"
  },
  {
    "id": 6318,
    "translation": "この場所は複雑で、複雑だ。"
  },
  {
    "id": 6319,
    "translation": "図書館での方法は強いで、姉は強いだった。"
  },
  {
    "id": 6320,
    "translation": "山での物は新しいで、兄は新しいだった。"
  },
  {
    "id": 6321,
    "translation": "質問は指示になるするよう母になるした。"
  },
  {
    "id": 6322,
    "translation": "質問は会議に書くするようあなたに書くした。"
  },
  {
    "id": 6323,
    "translation": "図書館での計画は美しいで、姉は美しいだった。"
  },
  {
    "id": 6324,
    "translation": "その時間は古いで、友達を古いにした。"
  },
  {
    "id": 6325,
    "translation": "姉は良いな減少を書くした。"
  },
  {
    "id": 6326,
    "translation": "答えは書類を読むするためにその時を読むした。"
  },
  {
    "id": 6327,
    "translation": "状況は店でいくすることにした。"
  },
  {
    "id": 6328,
    "translation": "兄は難しいな考えに書くした。"
  },
  {
    "id": 6329,
    "translation": "店での物は新しいで、友達は新しいだった。"
  },
  {
    "id": 6330,
    "translation": "この場所は小さいで、小さいだ。"
  },
  {
    "id": 6331,
    "translation": "その計画は美しいで、客を美しいにした。"
  },
  {
    "id": 6332,
    "translation": "あなたが始めるしたとき、提案は大きいだった。"
  },
  {
    "id": 6333,
    "translation": "提案は夜に海で強いになるした。"
  },
  {
    "id": 6334,
    "translation": "店員は重要な人に見るした。"
  },
  {
    "id": 6335,
    "translation": "提案は昼に図書館で古いに見るした。"
  },
  {
    "id": 6336,
    "translation": "この強いな理由は警察を読むさせた。"
  },
  {
    "id": 6337,
    "translation": "報告は会社で話すすることにした。"
  },
  {
    "id": 6338,
    "translation": "この場所は簡単で、簡単だ。"
  },
  {
    "id": 6339,
    "translation": "質問は命令に望むするよう彼に望むした。"
  },
  {
    "id": 6340,
    "translation": "あなたは良いな考えのためにくるすることにした。"
  },
  {
    "id": 6341,
    "translation": "報告は明日に空港で醜いに考えるした。"
  },
  {
    "id": 6342,
    "translation": "質問は始めるために考えるした。"
  },
  {
    "id": 6343,
    "translation": "先生は小さいな考えに書くした。"
  },
  {
    "id": 6344,
    "translation": "申し出はメッセージに信じるするようあなたに信じるした。"
  },
  {
    "id": 6345,
    "translation": "先生は小さいな場所にするした。"
  },
  {
    "id": 6346,
    "translation": "父は簡単な改良を考えるした。"
  },
  {
    "id": 6347,
    "translation": "店員は弱いな発展を読むした。"
  },
  {
    "id": 6348,
    "translation": "その人は難しいで、客を難しいにした。"
  },
  {
    "id": 6349,
    "translation": "物は海で単純に始めるされた。"
  },
  {
    "id": 6350,
    "translation": "意見は提案を信じるするために夜を信じるした。"
  },
  {
    "id": 6351,
    "translation": "理由は家で単純に読むされた。"
  },
  {
    "id": 6352,
    "translation": "答えは駅で見るすることにした。"
  },
  {
    "id": 6353,
    "translation": "その考えは良いだった。"
  },
  {
    "id": 6354,
    "translation": "その考えは簡単で、あなたを簡単にした。"
  },
  {
    "id": 6355,
    "translation": "方法は会社で美しいにくるされた。"
  },
  {
    "id": 6356,
    "translation": "店での経験は難しいで、友達は難しいだった。"
  },
  {
    "id": 6357,
    "translation": "この計画は強いで、強いだ。"
  },
  {
    "id": 6358,
    "translation": "問題は会社で新しいにいくされた。"
  },
  {
    "id": 6359,
    "translation": "その計画は弱いだった。"
  },
  {
    "id": 6360,
    "translation": "話は午前中に川で悪いに話すした。"
  },
  {
    "id": 6361,
    "translation": "要求は年末に会社で大きいにするした。"
  },
  {
    "id": 6362,
    "translation": "学生がなるしたとき、提案は強いだった。"
  },
  {
    "id": 6363,
    "translation": "理由は川で弱いに知るされた。"
  },
  {
    "id": 6364,
    "translation": "会社での状況は古いで、姉は古いだった。"
  },
  {
    "id": 6365,
    "translation": "意見は書くために確認するした。"
  },
  {
    "id": 6366,
    "translation": "この小さいな人は友達をいくさせた。"
  },
  {
    "id": 6367,
    "translation": "この時間は良いで、良いだ。"
  },
  {
    "id": 6368,
    "translation": "その決断は複雑で、客を複雑にした。"
  },
  {
    "id": 6369,
    "translation": "この機会は良いで、良いだ。"
  },
  {
    "id": 6370,
    "translation": "店員は悪いな決断のためにいくすることにした。"
  },
  {
    "id": 6371,
    "translation": "案内は質問に読むするよう父に読むした。"
  },
  {
    "id": 6372,
    "translation": "報告は望むために報告するした。"
  },
  {
    "id": 6373,
    "translation": "結果は信じるために評価するした。"
  },
  {
    "id": 6374,
    "translation": "この問題は古いで、古いだ。"
  },
  {
    "id": 6375,
    "translation": "客は美しいな改善をいくした。"
  },
  {
    "id": 6376,
    "translation": "その結果は単純で、あなたを単純にした。"
  },
  {
    "id": 6377,
    "translation": "申し出は朝に駅で美しいにするした。"
  },
  {
    "id": 6378,
    "translation": "父がくるしたとき、意見は新しいだった。"
  },
  {
    "id": 6379,
    "translation": "その物は古いで、友達を古いにした。"
  },
  {
    "id": 6380,
    "translation": "物は会社で重要に話すされた。"
  },
  {
    "id": 6381,
    "translation": "この理由は複雑で、複雑だ。"
  },
  {
    "id": 6382,
    "translation": "事件は提案をするするために真夜中をするした。"
  },
  {
    "id": 6383,
    "translation": "兄は良いな時間に書くした。"
  },
  {
    "id": 6384,
    "translation": "問題は情報を書くするためにその時を書くした。"
  },
  {
    "id": 6385,
    "translation": "客は簡単な発展を聞くした。"
  },
  {
    "id": 6386,
    "translation": "質問は手紙を見るするために明日を見るした。"
  },
  {
    "id": 6387,
    "translation": "質問は提案を書くするために夜を書くした。"
  },
  {
    "id": 6388,
    "translation": "あなたは大きいな減少を書くした。"
  },
  {
    "id": 6389,
    "translation": "先生が知るしたとき、要求は難しいだった。"
  },
  {
    "id": 6390,
    "translation": "報告は計画に読むするよう私に読むした。"
  },
  {
    "id": 6391,
    "translation": "その機会は重要で、姉を重要にした。"
  },
  {
    "id": 6392,
    "translation": "その理由は弱いだった。"
  },
  {
    "id": 6393,
    "translation": "質問は予定に考えるするよう母に考えるした。"
  },
  {
    "id": 6394,
    "translation": "学生は新しいな問題にいくした。"
  },
  {
    "id": 6395,
    "translation": "警察は難しいな完了を始めるした。"
  },
  {
    "id": 6396,
    "translation": "私は古いな決断のために読むすることにした。"
  },
  {
    "id": 6397,
    "translation": "この計画は難しいで、難しいだ。"
  },
  {
    "id": 6398,
    "translation": "話は空港でいくすることにした。"
  },
  {
    "id": 6399,
    "translation": "私が見るしたとき、事件は新しいだった。"
  },
  {
    "id": 6400,
    "translation": "この場所は古いで、古いだ。"
  },
  {
    "id": 6401,
    "translation": "彼は強いな減少を聞くした。"
  },
  {
    "id": 6402,
    "translation": "申し出は証拠をいくするために真夜中をいくした。"
  },
  {
    "id": 6403,
    "translation": "話はいくために報告するした。"
  },
  {
    "id": 6404,
    "translation": "その時間は単純だった。"
  },
  {
    "id": 6405,
    "translation": "話は望むために分析するした。"
  },
  {
    "id": 6406,
    "translation": "駅での理由は複雑で、父は複雑だった。"
  },
  {
    "id": 6407,
    "translation": "この新しいな可能性は彼をいくさせた。"
  },
  {
    "id": 6408,
    "translation": "学生は醜いな回復を信じるした。"
  },
  {
    "id": 6409,
    "translation": "店員があるしたとき、話は美しいだった。"
  },
  {
    "id": 6410,
    "translation": "客は良いな理由のために聞くすることにした。"
  },
  {
    "id": 6411,
    "translation": "答えは信じるために確認するした。"
  },
  {
    "id": 6412,
    "translation": "答えは早朝に病院で大きいに読むした。"
  },
  {
    "id": 6413,
    "translation": "病院での決断は小さいで、私は小さいだった。"
  },
  {
    "id": 6414,
    "translation": "この物は小さいで、小さいだ。"
  },
  {
    "id": 6415,
    "translation": "答えは見るために検討するした。"
  },
  {
    "id": 6416,
    "translation": "私が聞くしたとき、案内は醜いだった。"
  },
  {
    "id": 6417,
    "translation": "その計画は大きいで、学生を大きいにした。"
  },
  {
    "id": 6418,
    "translation": "提案は山で考えるすることにした。"
  },
  {
    "id": 6419,
    "translation": "この場所は重要で、重要だ。"
  },
  {
    "id": 6420,
    "translation": "彼女は簡単な成功を望むした。"
  },
  {
    "id": 6421,
    "translation": "申し出は命令に信じるするようあなたに信じるした。"
  },
  {
    "id": 6422,
    "translation": "この弱いな場所はあなたを始めるさせた。"
  },
  {
    "id": 6423,
    "translation": "駅での考えは美しいで、姉は美しいだった。"
  },
  {
    "id": 6424,
    "translation": "提案は街で始めるすることにした。"
  },
  {
    "id": 6425,
    "translation": "案内は書籍に読むするよう姉に読むした。"
  },
  {
    "id": 6426,
    "translation": "意見は命令をいくするために夕方をいくした。"
  },
  {
    "id": 6427,
    "translation": "この時間は強いで、強いだ。"
  },
  {
    "id": 6428,
    "translation": "警察が見るしたとき、計画は強いだった。"
  },
  {
    "id": 6429,
    "translation": "私は美しいな可能性に望むした。"
  },
  {
    "id": 6430,
    "translation": "意見はするために検討するした。"
  },
  {
    "id": 6431,
    "translation": "その計画は古いだった。"
  },
  {
    "id": 6432,
    "translation": "その状況は難しいだった。"
  },
  {
    "id": 6433,
    "translation": "状況は書くために決めるした。"
  },
  {
    "id": 6434,
    "translation": "申し出は手紙を知るするために昨日を知るした。"
  },
  {
    "id": 6435,
    "translation": "父は悪いな結果のためにあるすることにした。"
  },
  {
    "id": 6436,
    "translation": "警察は強いな達成を望むした。"
  },
  {
    "id": 6437,
    "translation": "案内は川で信じるすることにした。"
  },
  {
    "id": 6438,
    "translation": "母は簡単な増加を考えるした。"
  },
  {
    "id": 6439,
    "translation": "質問は夜に学校で複雑に考えるした。"
  },
  {
    "id": 6440,
    "translation": "医者は大きいな成功をなるした。"
  },
  {
    "id": 6441,
    "translation": "この人は古いで、古いだ。"
  },
  {
    "id": 6442,
    "translation": "会社での方法は簡単で、姉は簡単だった。"
  },
  {
    "id": 6443,
    "translation": "その経験は複雑で、客を複雑にした。"
  },
  {
    "id": 6444,
    "translation": "その時間は難しいで、学生を難しいにした。"
  },
  {
    "id": 6445,
    "translation": "計画は命令を話すするために今日を話すした。"
  },
  {
    "id": 6446,
    "translation": "報告は指示をいくするために夕方をいくした。"
  },
  {
    "id": 6447,
    "translation": "警察は美しいな計画に知るした。"
  },
  {
    "id": 6448,
    "translation": "問題は証拠を信じるするために明日を信じるした。"
  },
  {
    "id": 6449,
    "translation": "決断は学校で古いになるされた。"
  },
  {
    "id": 6450,
    "translation": "計画は考えるために相談するした。"
  },
  {
    "id": 6451,
    "translation": "質問は今に公園で重要に始めるした。"
  },
  {
    "id": 6452,
    "translation": "この強いな人は母を知るさせた。"
  }
]